ortega/STPoint.py
ortega/__init__.py
ortega/common.py
ortega/ellipses.py
ortega/ortega.py
ortega/output.py
ortega/visualization.py
ortega-1.0.17.dist-info/LICENSE
ortega-1.0.17.dist-info/METADATA
ortega-1.0.17.dist-info/WHEEL
ortega-1.0.17.dist-info/top_level.txt
ortega-1.0.17.dist-info/RECORD
