Metadata-Version: 2.1
Name: ortega
Version: 1.0.17
Summary: ORTEGA
Home-page: https://github.com/move-ucsb/ORTEGA
Author: MOVE lab@UCSB
Author-email: rongxiangsu@ucsb.edu
License: MIT
Platform: UNKNOWN
Requires-Dist: numpy
Requires-Dist: pandas
Requires-Dist: shapely
Requires-Dist: attrs
Requires-Dist: matplotlib
Requires-Dist: typing-extensions
